cerc_co2_emission-0.1.0.5.data/data/co2_emission/requirements.txt
co2_emission/__init__.py
co2_emission/co2_emission.py
co2_emission/version.py
cerc_co2_emission-0.1.0.5.dist-info/METADATA
cerc_co2_emission-0.1.0.5.dist-info/WHEEL
cerc_co2_emission-0.1.0.5.dist-info/top_level.txt
cerc_co2_emission-0.1.0.5.dist-info/RECORD
